[
  {
    "file": "2026-05-08-postmarket.json",
    "stem": "2026-05-08-postmarket",
    "updated_at": "2026-05-09T03:54:07Z"
  },
  {
    "file": "2026-05-08-premarket.json",
    "stem": "2026-05-08-premarket",
    "updated_at": "2026-05-09T03:54:07Z"
  },
  {
    "file": "2026-05-11-premarket.json",
    "stem": "2026-05-11-premarket",
    "updated_at": "2026-05-11T14:21:15Z"
  },
  {
    "file": "2026-05-11-postmarket.json",
    "stem": "2026-05-11-postmarket",
    "updated_at": "2026-05-12T02:21:15Z"
  },
  {
    "file": "2026-05-12-premarket.json",
    "stem": "2026-05-12-premarket",
    "updated_at": "2026-05-12T12:00:56Z"
  },
  {
    "file": "2026-05-12-postmarket.json",
    "stem": "2026-05-12-postmarket",
    "updated_at": "2026-05-12T21:02:23Z"
  },
  {
    "file": "2026-05-13-premarket.json",
    "stem": "2026-05-13-premarket",
    "updated_at": "2026-05-13T12:02:30Z"
  },
  {
    "file": "2026-05-14-premarket.json",
    "stem": "2026-05-14-premarket",
    "updated_at": "2026-05-14T12:05:02Z"
  },
  {
    "file": "2026-05-14-postmarket.json",
    "stem": "2026-05-14-postmarket",
    "updated_at": "2026-05-14T22:39:58Z"
  },
  {
    "file": "2026-05-18-premarket.json",
    "stem": "2026-05-18-premarket",
    "updated_at": "2026-05-18T12:02:00Z"
  },
  {
    "file": "2026-05-18-postmarket.json",
    "stem": "2026-05-18-postmarket",
    "updated_at": "2026-05-18T21:01:20Z"
  },
  {
    "file": "2026-05-20-postmarket.json",
    "stem": "2026-05-20-postmarket",
    "updated_at": "2026-05-20T21:01:38Z"
  },
  {
    "file": "2026-05-22-postmarket.json",
    "stem": "2026-05-22-postmarket",
    "updated_at": "2026-05-23T00:02:28Z"
  },
  {
    "file": "2026-05-23-postmarket.json",
    "stem": "2026-05-23-postmarket",
    "updated_at": "2026-05-24T06:53:52Z"
  },
  {
    "file": "2026-05-24-postmarket.json",
    "stem": "2026-05-24-postmarket",
    "updated_at": "2026-05-24T15:53:08Z"
  }
]